hepi/__init__.py
hepi/_version.py
hepi/fast.py
hepi/input.py
hepi/interpolate.py
hepi/load.py
hepi/order.py
hepi/output.py
hepi/particles.py
hepi/results.py
hepi/util.py
hepi/data/__init__.py
hepi/data/data.py
hepi/data/json/13000_hino_deg_1000022_-1000024_NNLL.json
hepi/data/json/13000_hino_deg_1000022_1000023_NNLL.json
hepi/data/json/13000_hino_deg_1000022_1000024_NNLL.json
hepi/data/json/13000_hino_deg_1000024_-1000024_NNLL.json
hepi/data/json/13000_hino_nondeg_1000022_1000023_NNLL.json
hepi/data/json/13000_hino_nondeg_1000023_-1000024_NNLL.json
hepi/data/json/13000_hino_nondeg_1000023_1000024_NNLL.json
hepi/data/json/13000_hino_nondeg_1000024_-1000024_NNLL.json
hepi/data/json/13000_sleptons_1000011_-1000011_NNLL.json
hepi/data/json/13000_sleptons_1000015_-1000015_NNLL.json
hepi/data/json/13000_sleptons_2000011_-2000011_NNLL.json
hepi/data/json/13000_sneutrinos_-1000011_1000012_NNLL.json
hepi/data/json/13000_sneutrinos_-1000012_1000012_NNLL.json
hepi/data/json/13000_sneutrinos_-1000015_1000016_NNLL.json
hepi/data/json/13000_sneutrinos_1000011_-1000012_NNLL.json
hepi/data/json/13000_sneutrinos_1000015_-1000016_NNLL.json
hepi/data/json/13000_wino_1000023_-1000024_NNLL.json
hepi/data/json/13000_wino_1000023_1000024_NNLL.json
hepi/data/json/13000_wino_1000024_-1000024_NNLL.json
hepi/data/json/13000_wino_sq_dep_1000023_-1000024_LO.json
hepi/data/json/13000_wino_sq_dep_1000023_-1000024_NLO.json
hepi/data/json/13000_wino_sq_dep_1000023_-1000024_NNLL.json
hepi/data/json/13000_wino_sq_dep_1000023_1000024_LO.json
hepi/data/json/13000_wino_sq_dep_1000023_1000024_NLO.json
hepi/data/json/13000_wino_sq_dep_1000023_1000024_NNLL.json
hepi/data/json/13000_wino_sq_dep_1000024_-1000024_LO.json
hepi/data/json/13000_wino_sq_dep_1000024_-1000024_NLO.json
hepi/data/json/13000_wino_sq_dep_1000024_-1000024_NNLL.json
hepi/data/json/13600_hino_deg_1000022_-1000024_NNLL.json
hepi/data/json/13600_hino_deg_1000022_1000023_NNLL.json
hepi/data/json/13600_hino_deg_1000022_1000024_NNLL.json
hepi-0.3.3.dist-info/METADATA
hepi-0.3.3.dist-info/WHEEL
hepi-0.3.3.dist-info/entry_points.txt
hepi-0.3.3.dist-info/licenses/LICENSE
hepi-0.3.3.dist-info/RECORD
