Metadata-Version: 2.4
Name: hepi
Version: 0.3.3
Summary: Interface to High Energy Physics tools.
Project-URL: Documentation, https://hepi.readthedocs.io/
Project-URL: Issues, https://github.com/APN-Pucky/HEPi/issues
Project-URL: Source, https://github.com/APN-Pucky/HEPi
Author-email: Alexander Puck Neuwirth <alexander@neuwirth-informatik.de>
License-File: LICENSE
Classifier: Development Status :: 4 - Beta
Classifier: Intended Audience :: Developers
Classifier: Intended Audience :: Science/Research
Classifier: Programming Language :: Python
Classifier: Programming Language :: Python :: 3.9
Classifier: Programming Language :: Python :: 3.10
Classifier: Programming Language :: Python :: 3.11
Classifier: Programming Language :: Python :: 3.12
Classifier: Programming Language :: Python :: 3.13
Classifier: Programming Language :: Python :: Implementation :: CPython
Classifier: Programming Language :: Python :: Implementation :: PyPy
Classifier: Topic :: Scientific/Engineering
Requires-Python: >=3.9
Requires-Dist: matplotlib
Requires-Dist: numpy
Requires-Dist: pandas>=1.0.0
Requires-Dist: particle
Requires-Dist: pqdm
Requires-Dist: pyslha
Requires-Dist: scipy>=1.7.0
Requires-Dist: smpl>=1.5.0
Requires-Dist: sympy
Requires-Dist: uncertainties>=3.2.3
Requires-Dist: validators
Provides-Extra: dev
Requires-Dist: ipython; extra == 'dev'
Requires-Dist: jupyter; extra == 'dev'
Requires-Dist: jupyterlab; extra == 'dev'
Requires-Dist: pre-commit; extra == 'dev'
Provides-Extra: docs
Requires-Dist: jupyter-sphinx; extra == 'docs'
Requires-Dist: myst-parser; extra == 'docs'
Requires-Dist: nbsphinx; extra == 'docs'
Requires-Dist: numpydoc; extra == 'docs'
Requires-Dist: pandoc; extra == 'docs'
Requires-Dist: sphinx-autoapi; extra == 'docs'
Requires-Dist: sphinx-autobuild; extra == 'docs'
Requires-Dist: sphinx-math-dollar; extra == 'docs'
Requires-Dist: sphinx-rtd-theme; extra == 'docs'
Requires-Dist: sphinx<8.0.0; extra == 'docs'
Requires-Dist: sphinxcontrib-napoleon; extra == 'docs'
Requires-Dist: toml; extra == 'docs'
Provides-Extra: lhapdf
Requires-Dist: lhapdf; extra == 'lhapdf'
Provides-Extra: test
Requires-Dist: pytest; extra == 'test'
Requires-Dist: pytest-cov; extra == 'test'
Requires-Dist: pytest-line-profiler-apn>=0.1.3; extra == 'test'
Requires-Dist: pytest-profiling; extra == 'test'
